ipystream/__init__.py
ipystream/async_debounce.py
ipystream/renderer.py
ipystream/stream.py
ipystream/utils.py
ipystream/voila/__init__.py
ipystream/voila/auth_wall_limit.py
ipystream/voila/cookie.py
ipystream/voila/documentation.py
ipystream/voila/error_handler.py
ipystream/voila/kernel.py
ipystream/voila/kernel_heartbeat.py
ipystream/voila/login.py
ipystream/voila/patch_voila.py
ipystream/voila/patched_generator.py
ipystream/voila/patched_generator2.py
ipystream/voila/run_raw.py
ipystream/voila/spinned.py
ipystream/voila/utils.py
ipystream/voila/utils_log.py
ipystream/voila/watchdog_raw.py
ipystream/widget_currents_children.py
ipystream-0.1.14.dist-info/LICENSE
ipystream-0.1.14.dist-info/METADATA
ipystream-0.1.14.dist-info/WHEEL
ipystream-0.1.14.dist-info/RECORD
